README.md
setup.cfg
setup.py
hjn/H8mess.py
hjn/__init__.py
hjn/cinradHJN.py
hjn/examMeso.py
hjn/hjnDAAS.py
hjn/hjnFTP.py
hjn/hjnGIS.py
hjn/hjnGPU.py
hjn/hjnIDW.py
hjn/hjnKDTree.py
hjn/hjnLAPSTransform.py
hjn/hjnMiscellaneous.py
hjn/hjnProj.py
hjn/inotify.py
hjn/matplotlibMess.py
hjn/mkNCHJN.py
hjn/newTypeRadar.py
hjn/test.py
hjn/tlogP.py
hjn.egg-info/PKG-INFO
hjn.egg-info/SOURCES.txt
hjn.egg-info/dependency_links.txt
hjn.egg-info/not-zip-safe
hjn.egg-info/top_level.txt