Metadata-Version: 2.1
Name: hjn
Version: 0.1.144
Summary: hjn in CMA
Home-page:  
Author: hjn
Author-email: hujunnan2@126.com
License: MIT
